pycistem/__init__.py
pycistem/config.py
pycistem/core/__init__.py
pycistem/core/core.cpp
pycistem/core/core.cpython-311-x86_64-linux-gnu.so
pycistem/core/database.cpp
pycistem/core/euler_search.cpp
pycistem/core/run_profiles.cpp
pycistem/database/__init__.py
pycistem/programs/__init__.py
pycistem/programs/_cistem_constants.py
pycistem/programs/apply_ctf.py
pycistem/programs/cistem_program.py
pycistem/programs/ctffind.py
pycistem/programs/estimate_beamtilt.py
pycistem/programs/match_template.py
pycistem/programs/reconstruct3d.py
pycistem/programs/refine_ctf.py
pycistem/programs/refine_template.py
pycistem/programs/refine_template_dev.py
pycistem/programs/refine_template_niko.py
pycistem/programs/resample.py
pycistem/programs/run_profile.py
pycistem/programs/unblur.py
pycistem/programs/unblur_patch.py
pycistem/utils/__init__.py
pycistem/utils/extract_particles.py
pycistem/utils/move_class_into_unbinned_particle_stack.py
pycistem/utils/order_by_class_occupancy.py
pycistem/utils/plot_class_occupancy.py
pycistem/utils/plot_classification_fsc_movie.py
pycistem/utils/plot_occupancy_by_condition.py
pycistem.libs/libgomp-98b21ff3.so.1.0.0
pycistem-0.6.0.dist-info/METADATA
pycistem-0.6.0.dist-info/WHEEL
pycistem-0.6.0.dist-info/RECORD
pycistem-0.6.0.dist-info/licenses/LICENSE
pycistem-0.6.0.dist-info/sboms/auditwheel.cdx.json
