Metadata-Version: 2.4
Name: pycistem
Version: 0.6.0
Summary: Python tools to run cisTEM programs and code
Project-URL: Documentation, https://github.com/jojoelfe/pycistem#readme
Project-URL: Issues, https://github.com/jojoelfe/pycistem/issues
Project-URL: Source, https://github.com/jojoelfe/pycistem
Author-email: Johannes Elferich <jojotux123@hotmail.com>
License:                                  Apache License
License-File: LICENSE
Classifier: Development Status :: 4 - Beta
Classifier: Programming Language :: Python
Classifier: Programming Language :: Python :: 3.9
Classifier: Programming Language :: Python :: 3.10
Classifier: Programming Language :: Python :: 3.11
Classifier: Programming Language :: Python :: Implementation :: CPython
Classifier: Programming Language :: Python :: Implementation :: PyPy
Requires-Python: >=3.9
Requires-Dist: appdirs
Requires-Dist: mdocfile
Requires-Dist: mrcfile
Requires-Dist: pandas
Requires-Dist: psutil
Requires-Dist: pyyaml
Requires-Dist: rich
Requires-Dist: setuptools<60
Requires-Dist: starfile
